desktop4mistral/__init__.py
desktop4mistral/chat_window.py
desktop4mistral/commands.py
desktop4mistral/main.py
desktop4mistral/markdown_handler.py
desktop4mistral/speaker.py
desktop4mistral/state.py
desktop4mistral/utils.py
desktop4mistral/fonts/FiraCode-VariableFont_wght.ttf
desktop4mistral/helpers/__init__.py
desktop4mistral/helpers/wikitomarkdown.py
desktop4mistral/mistral/__init__.py
desktop4mistral/mistral/client.py
desktop4mistral-0.1.2.dist-info/licenses/LICENSE
desktop4mistral-0.1.2.dist-info/METADATA
desktop4mistral-0.1.2.dist-info/WHEEL
desktop4mistral-0.1.2.dist-info/entry_points.txt
desktop4mistral-0.1.2.dist-info/top_level.txt
desktop4mistral-0.1.2.dist-info/RECORD
