Metadata-Version: 2.4
Name: desktop4mistral
Version: 0.1.2
Summary: A powerful desktop client for Mistral LLMs
Home-page: https://github.com/hathibelagal-dev/desktop4mistral
Author: Ashraff Hathibelagal
Project-URL: Source, https://github.com/hathibelagal-dev/desktop4mistral
Project-URL: Tracker, https://github.com/hathibelagal-dev/desktop4mistral/issues
Keywords: ai text-to-speech speech-synthesis nlp transformer voice
Classifier: Development Status :: 4 - Beta
Classifier: Intended Audience :: Developers
Classifier: License :: OSI Approved :: GNU General Public License v3 (GPLv3)
Classifier: Programming Language :: Python :: 3.11
Classifier: Programming Language :: Python :: 3.12
Requires-Python: >=3.11
License-File: LICENSE
Requires-Dist: PySide6
Requires-Dist: requests
Requires-Dist: markdown
Requires-Dist: wikipedia
Requires-Dist: markdownify
Requires-Dist: git2string
Requires-Dist: str2speech>=0.3.0
Requires-Dist: sounddevice
Requires-Dist: scipy
Dynamic: author
Dynamic: classifier
Dynamic: description
Dynamic: description-content-type
Dynamic: home-page
Dynamic: keywords
Dynamic: license-file
Dynamic: project-url
Dynamic: requires-dist
Dynamic: requires-python
Dynamic: summary
